ngp/__init__.py
ngp/__init__.py~
ngp/__main__.py
ngp-1.0.1.dist-info/METADATA
ngp-1.0.1.dist-info/WHEEL
ngp-1.0.1.dist-info/entry_points.txt
ngp-1.0.1.dist-info/RECORD
